setup.py
clustering/__init__.py
clustering/cluster/__init__.py
clustering/cluster/k_means.py
clustering_jhk/__init__.py
clustering_jhk/base.py
clustering_jhk.egg-info/PKG-INFO
clustering_jhk.egg-info/SOURCES.txt
clustering_jhk.egg-info/dependency_links.txt
clustering_jhk.egg-info/not-zip-safe
clustering_jhk.egg-info/top_level.txt
clustering_jhk/cluster/__init__.py
clustering_jhk/cluster/k_means.py
clustering_jhk/cluster/k_means_elkan.py
clustering_jhk/cluster/k_means_fast.py
clustering_jhk/dataset/__init__.py
clustering_jhk/metrics/__init__.py
clustering_jhk/metrics/pairwise.py
clustering_jhk/metrics/supervised.py
clustering_jhk/utils/__init__.py
clustering_jhk/utils/extmath.py
clustering_jhk/utils/validation.py