Metadata-Version: 1.1
Name: clustering-jhk
Version: 0.2
Summary: practice for K-Means algorithm
Home-page: UNKNOWN
Author: Ji-Hoon Kim
Author-email: genesis717.jhk@gmail.com
License: MIT
Platform: UNKNOWN
Classifier: Programming Language :: Python :: 3.5
Classifier: Programming Language :: Python :: 3.6
Classifier: Programming Language :: Python :: 3.7
